torch_nl/__init__.py
torch_nl/geometry.py
torch_nl/linked_cell.py
torch_nl/naive_impl.py
torch_nl/neighbor_list.py
torch_nl/test_nl.py
torch_nl/timer.py
torch_nl/utils.py
torch_nl-0.3.dist-info/LICENSE
torch_nl-0.3.dist-info/METADATA
torch_nl-0.3.dist-info/WHEEL
torch_nl-0.3.dist-info/top_level.txt
torch_nl-0.3.dist-info/zip-safe
torch_nl-0.3.dist-info/RECORD
