Metadata-Version: 2.1
Name: torch-nl
Version: 0.3
Summary: TorchScript-able neighbor lists implementations (linear and quadratic scaling) for molecular modeling
Author: Félix Musil
License: MIT
Classifier: Programming Language :: Python :: 3.7
Classifier: Topic :: Scientific/Engineering :: Chemistry
Classifier: Topic :: Scientific/Engineering :: Physics
Requires-Python: >=3.8
License-File: LICENSE
Requires-Dist: ase
Requires-Dist: numpy
Requires-Dist: torch (>=1.10)
Requires-Dist: pytest
Requires-Dist: black[jupyter]
